kgraph/__init__.py
kgraph/clustering.py
kgraph/graph.py
kgraph/metrics.py
kgraph_lib-0.1.1.dist-info/METADATA
kgraph_lib-0.1.1.dist-info/WHEEL
kgraph_lib-0.1.1.dist-info/top_level.txt
kgraph_lib-0.1.1.dist-info/RECORD
